pdmodel/GoogleSTT.py
pdmodel/__init__.py
pdmodel/deployModel.py
pdmodel/edge_video.py
pdmodel/gaitExtraction.py
pdmodel/gaitFeaturesExtraction.py
pdmodel/gen_skes.py
pdmodel/handExtraction.py
pdmodel/handFeaturesExtraction.py
pdmodel/handKeypoints.py
pdmodel/settings.py
pdmodel/utils.py
pdmodel/voiceFeatureExtraction.py
pdmodel-0.0.2.dist-info/LICENSE
pdmodel-0.0.2.dist-info/METADATA
pdmodel-0.0.2.dist-info/WHEEL
pdmodel-0.0.2.dist-info/top_level.txt
pdmodel-0.0.2.dist-info/RECORD
