Metadata-Version: 2.1
Name: pdmodel
Version: 0.0.2
Summary: An AI tool for screening Parkinson's disease
Home-page: UNKNOWN
Author: leolim3092
Author-email: your@email.com
License: UNKNOWN
Platform: UNKNOWN
Classifier: Programming Language :: Python :: 3
Classifier: License :: OSI Approved :: Apache Software License
Classifier: Operating System :: OS Independent
License-File: LICENSE
Requires-Dist: numpy
Requires-Dist: matplotlib
